django_api_vue/__init__.py
django_api_vue/constants.py
django_api_vue/enums.py
django_api_vue/errors.py
django_api_vue/fields.py
django_api_vue/mixins.py
django_api_vue/models.py
django_api_vue/params.py
django_api_vue/returns.py
django_api_vue/views.py
django_api_vue-0.1.4.dist-info/LICENSE
django_api_vue-0.1.4.dist-info/METADATA
django_api_vue-0.1.4.dist-info/WHEEL
django_api_vue-0.1.4.dist-info/top_level.txt
django_api_vue-0.1.4.dist-info/RECORD
