Metadata-Version: 2.1
Name: django-api-vue
Version: 0.1.4
Summary: A Django framework tailored for APIs with Vue.js frontend integration.
Author: Song Hao
Author-email: 173077850@qq.com
Classifier: Programming Language :: Python :: 3
Classifier: License :: OSI Approved :: MIT License
Classifier: Operating System :: OS Independent
License-File: LICENSE
Requires-Dist: Django >=3.2
